{
  "@id": "https://raw.githubusercontent.com/talos/docker4data/master/data/2013_proposed_budget_general_fund_expenditures_by_appropriation_unit/data.json", 
  "data": {
    "@id": "http://www.opendatacache.com/data.kingcounty.gov/api/views/yj3s-xdaz/rows.csv", 
    "type": "csv"
  }, 
  "description": "King County budget proposed September 2012 by Executive for 2013, General Fund Expenditures By Appropriation Unit. The General Fund is an annual budget for the 2013/2014 Biennium. See http://www.kingcounty.gov/budget for more.", 
  "maintainer": {
    "@id": "https://github.com/talos/docker4data"
  }, 
  "metadata": {
    "attribution": "King County Executive", 
    "category": "Budget", 
    "description": "King County budget proposed September 2012 by Executive for 2013, General Fund Expenditures By Appropriation Unit. The General Fund is an annual budget for the 2013/2014 Biennium. See http://www.kingcounty.gov/budget for more.", 
    "socrata": {
      "@id": "http://www.opendatacache.com/data.kingcounty.gov/api/views/yj3s-xdaz.json"
    }
  }, 
  "name": "2013 Proposed Budget, General Fund Expenditures By Appropriation Unit", 
  "schema": {
    "columns": [
      {
        "name": "section", 
        "type": "text"
      }, 
      {
        "name": "strategic_plan", 
        "type": "text"
      }, 
      {
        "name": "_1", 
        "type": "real"
      }, 
      {
        "name": "_2", 
        "type": "real"
      }, 
      {
        "name": "_3", 
        "type": "real"
      }, 
      {
        "name": "percent_change", 
        "type": "text"
      }
    ]
  }, 
  "schemaName": "socrata/data.kingcounty.gov", 
  "tableName": "2013_proposed_budget_general_fund_expenditures_by_appropriation_unit"
}