{
  "data": "http://www.opendatacache.com/data.cityofboston.gov/api/views/t85d-b449/rows.csv", 
  "description": "The list of all property addresses in the city", 
  "maintainer": {
    "@id": "https://github.com/talos/docker4data"
  }, 
  "metadata": {
    "attribution": "Department of Innovation and Technology", 
    "category": "City Services", 
    "description": "The list of all property addresses in the city", 
    "socrata": {
      "@id": "http://www.opendatacache.com/data.cityofboston.gov/api/views/t85d-b449.json"
    }
  }, 
  "name": "Master Address List", 
  "schema": "socrata/data.cityofboston.gov", 
  "status": "needs review", 
  "table": "master_address_list"
}