{
  "@id": "https://raw.githubusercontent.com/talos/docker4data/master/data/socrata_ny_port_authority_trans_hudson_corporation_path_averag/data.json", 
  "data": {
    "@id": "http://www.opendatacache.com/data.ny.gov/api/views/p7e4-ipty/rows.csv"
  }, 
  "maintainer": {
    "@id": "https://github.com/talos/docker4data"
  }, 
  "metadata": {
    "socrata": "http://www.opendatacache.com/data.ny.gov/api/views/p7e4-ipty.json"
  }, 
  "name": "socrata_ny_port_authority_trans_hudson_corporation_path_averag", 
  "schema": {
    "columns": [
      {
        "name": "year", 
        "type": "real"
      }, 
      {
        "name": "month", 
        "type": "text"
      }, 
      {
        "name": "average_weekday_trips", 
        "type": "real"
      }, 
      {
        "name": "average_saturday_trips", 
        "type": "real"
      }, 
      {
        "name": "average_sunday_trips", 
        "type": "real"
      }
    ]
  }
}