{
  "@id": "https://raw.githubusercontent.com/talos/docker4data/master/data/socrata_seattle_transit_communities/data.json", 
  "data": {
    "@id": "http://www.opendatacache.com/data.seattle.gov/api/views/ndi9-2pye/rows.csv"
  }, 
  "maintainer": {
    "@id": "https://github.com/talos/docker4data"
  }, 
  "metadata": {
    "socrata": "http://www.opendatacache.com/data.seattle.gov/api/views/ndi9-2pye.json"
  }, 
  "name": "socrata_seattle_transit_communities", 
  "schema": {
    "columns": [
      {
        "name": "name", 
        "type": "text"
      }, 
      {
        "name": "typology", 
        "type": "text"
      }, 
      {
        "name": "current_conditions", 
        "type": "text"
      }, 
      {
        "name": "future_needs_priorities", 
        "type": "text"
      }, 
      {
        "name": "district", 
        "type": "text"
      }, 
      {
        "name": "neighborhood_plan", 
        "type": "text"
      }, 
      {
        "name": "status_check", 
        "type": "text"
      }, 
      {
        "name": "city_planning", 
        "type": "text"
      }, 
      {
        "name": "major_transit_project", 
        "type": "text"
      }
    ]
  }
}