{
  "data": "http://www.opendatacache.com/data.oregon.gov/api/views/2z9p-6rz2/rows.csv", 
  "description": "General address/location information of Oregon public libraries (including branches)", 
  "maintainer": {
    "@id": "https://github.com/talos/docker4data"
  }, 
  "metadata": {
    "attribution": "Oregon State Library", 
    "category": "Education", 
    "description": "General address/location information of Oregon public libraries (including branches)", 
    "socrata": {
      "@id": "http://www.opendatacache.com/data.oregon.gov/api/views/2z9p-6rz2.json"
    }
  }, 
  "name": "Oregon Public Libraries", 
  "schema": "socrata/data.oregon.gov", 
  "status": "needs review", 
  "table": "oregon_public_libraries"
}