{
  "data": "http://www.opendatacache.com/data.kingcounty.gov/api/views/6z8h-tt4v/rows.csv", 
  "description": "Charitable contributions from King County employees", 
  "maintainer": {
    "@id": "https://github.com/talos/docker4data"
  }, 
  "metadata": {
    "attribution": "King County Employee Giving Program", 
    "category": "Employees", 
    "description": "Charitable contributions from King County employees", 
    "socrata": {
      "@id": "http://www.opendatacache.com/data.kingcounty.gov/api/views/6z8h-tt4v.json"
    }
  }, 
  "name": "Employee giving statistics - 2013", 
  "schema": "socrata/data.kingcounty.gov", 
  "status": "needs review", 
  "table": "employee_giving_statistics_2013"
}