{
  "data": "http://www.opendatacache.com/data.ny.gov/api/views/q88j-j2mi/rows.csv", 
  "description": "Included in this data set are data elements that will help the public identify agencies that are certified to operate programs for runaway and homeless youth. These programs are available to assist runaway and homeless youth in emergency situation and provide independent living skills for youth in transition. Data elements include the agency name, agency business address, phone number, website and type of program offered.", 
  "maintainer": {
    "@id": "https://github.com/talos/docker4data"
  }, 
  "metadata": {
    "attribution": "New York State Office of Children and Family Services", 
    "category": "Human Services", 
    "description": "Included in this data set are data elements that will help the public identify agencies that are certified to operate programs for runaway and homeless youth. These programs are available to assist runaway and homeless youth in emergency situation and provide independent living skills for youth in transition. Data elements include the agency name, agency business address, phone number, website and type of program offered.", 
    "socrata": {
      "@id": "http://www.opendatacache.com/data.ny.gov/api/views/q88j-j2mi.json"
    }
  }, 
  "name": "Runaway And Homeless Youth Programs", 
  "schema": "socrata/data.ny.gov", 
  "status": "needs review", 
  "table": "runaway_and_homeless_youth_programs"
}