{
  "data": "http://www.opendatacache.com/data.maryland.gov/api/views/8aku-y93i/rows.csv", 
  "description": "To help Maryland homeowners invest in clean energy, the Maryland Energy Administration provides grants for clean burning wood stoves that displace electric, non-natural gas fossil fuel heating systems or old wood stoves.\r\n\r\nMore information is available on the program's website at: http://energy.maryland.gov/Residential/woodstoves/", 
  "maintainer": {
    "@id": "https://github.com/talos/docker4data"
  }, 
  "metadata": {
    "attribution": "Maryland Energy Administration", 
    "category": "Energy and Environment", 
    "description": "To help Maryland homeowners invest in clean energy, the Maryland Energy Administration provides grants for clean burning wood stoves that displace electric, non-natural gas fossil fuel heating systems or old wood stoves.\r\n\r\nMore information is available on the program's website at: http://energy.maryland.gov/Residential/woodstoves/", 
    "socrata": {
      "@id": "http://www.opendatacache.com/data.maryland.gov/api/views/8aku-y93i.json"
    }
  }, 
  "name": "Clean Burning Wood Stove Grants", 
  "schema": "socrata/data.maryland.gov", 
  "status": "needs review", 
  "table": "clean_burning_wood_stove_grants"
}