{
  "maintainer": {
    "@id": "https://github.com/talos/docker4data"
  }, 
  "schema": {
    "columns": [
      {
        "type": "text", 
        "name": "borough"
      }, 
      {
        "type": "text", 
        "name": "name"
      }, 
      {
        "type": "smallint", 
        "name": "zip_code"
      }, 
      {
        "type": "text", 
        "name": "facility_id"
      }, 
      {
        "type": "text", 
        "name": "operator"
      }, 
      {
        "type": "text", 
        "name": "certificate_number"
      }, 
      {
        "type": "smallint", 
        "name": "number_of_beds"
      }, 
      {
        "type": "tinyint", 
        "name": "assisted_living_program_beds"
      }, 
      {
        "type": "tinyint", 
        "name": "assisted_living_residence_alr_beds"
      }, 
      {
        "type": "tinyint", 
        "name": "enhanced_alr_beds"
      }, 
      {
        "type": "tinyint", 
        "name": "special_needs_alr_beds"
      }, 
      {
        "type": "text", 
        "name": "facility"
      }, 
      {
        "type": "text", 
        "name": "type"
      }, 
      {
        "type": "text", 
        "name": "location"
      }
    ]
  }, 
  "@id": "https://raw.githubusercontent.com/talos/docker4data/master/data/socrata_bronx_lehman_cuny_bronx_adult_care_facilities/data.json", 
  "name": "socrata_bronx_lehman_cuny_bronx_adult_care_facilities", 
  "data": {
    "@id": "http://www.opendatacache.com/bronx.lehman.cuny.edu/api/views/kski-75ku/rows.csv"
  }
}