{
  "@id": "https://raw.githubusercontent.com/talos/docker4data/master/data/socrata_finances_worldbank_world_bank_finances_data_dictionary/data.json", 
  "data": {
    "@id": "http://www.opendatacache.com/finances.worldbank.org/api/views/wc6g-9zmq/rows.csv"
  }, 
  "maintainer": {
    "@id": "https://github.com/talos/docker4data"
  }, 
  "metadata": {
    "socrata": "http://www.opendatacache.com/finances.worldbank.org/api/views/wc6g-9zmq.json"
  }, 
  "name": "socrata_finances_worldbank_world_bank_finances_data_dictionary", 
  "schema": {
    "columns": [
      {
        "name": "dataset_name", 
        "type": "text"
      }, 
      {
        "name": "data_element", 
        "type": "text"
      }, 
      {
        "name": "description", 
        "type": "text"
      }
    ]
  }
}