{
  "data": "http://www.opendatacache.com/datacatalog.cookcountyil.gov/api/views/gywr-fjeh/rows.csv", 
  "description": "This check register provides a cumulative record of payments to County suppliers, vendors and other payees as approved by the Cook County Board of Commissioners. Data covers December 2009 through May 2015.", 
  "maintainer": {
    "@id": "https://github.com/talos/docker4data"
  }, 
  "metadata": {
    "attribution": "Cook County Office of the Comptroller", 
    "category": "Finance & Administration", 
    "description": "This check register provides a cumulative record of payments to County suppliers, vendors and other payees as approved by the Cook County Board of Commissioners. Data covers December 2009 through June 2015.", 
    "socrata": {
      "@id": "http://www.opendatacache.com/datacatalog.cookcountyil.gov/api/views/gywr-fjeh.json"
    }
  }, 
  "name": "Cook County Check Register", 
  "schema": "socrata/datacatalog.cookcountyil.gov", 
  "status": "needs review", 
  "table": "cook_county_check_register"
}