{
  "@id": "https://raw.githubusercontent.com/talos/docker4data/master/data/socrata_illinois_ssmma_blue_island_historic_properties/data.json", 
  "data": {
    "@id": "http://www.opendatacache.com/data.illinois.gov/api/views/hgt2-8jmr/rows.csv", 
    "type": "csv"
  }, 
  "description": "This dataset is an inventory of all historic properties within the City of Blue Island, Illinois.", 
  "maintainer": {
    "@id": "https://github.com/talos/docker4data"
  }, 
  "metadata": {
    "attribution": "South Suburban Mayors and Managers Association", 
    "category": "Municipality", 
    "description": "This dataset is an inventory of all historic properties within the City of Blue Island, Illinois.", 
    "socrata": {
      "@id": "http://www.opendatacache.com/data.illinois.gov/api/views/hgt2-8jmr.json"
    }
  }, 
  "name": "SSMMA Blue Island Historic Properties", 
  "schema": {
    "columns": [
      {
        "name": "description_style_or_type_shape_or_plan_roof_shape_decorative_work_etc", 
        "type": "text"
      }, 
      {
        "name": "if_not_currently_listed_recommend", 
        "type": "text"
      }, 
      {
        "name": "major_physical_changes_from_original_construction_and_dates", 
        "type": "text"
      }, 
      {
        "name": "a_chimney", 
        "type": "text"
      }, 
      {
        "name": "accessory_buildings_site", 
        "type": "text"
      }, 
      {
        "name": "addition", 
        "type": "text"
      }, 
      {
        "name": "addition_notes", 
        "type": "text"
      }, 
      {
        "name": "architect_builder", 
        "type": "text"
      }, 
      {
        "name": "architectural_style", 
        "type": "text"
      }, 
      {
        "name": "cladding_material", 
        "type": "text"
      }, 
      {
        "name": "condition", 
        "type": "text"
      }, 
      {
        "name": "construction_date", 
        "type": "text"
      }, 
      {
        "name": "covering_material", 
        "type": "text"
      }, 
      {
        "name": "district_zone", 
        "type": "text"
      }, 
      {
        "name": "door_details", 
        "type": "text"
      }, 
      {
        "name": "door_details_2", 
        "type": "text"
      }, 
      {
        "name": "e_roofing_if_decorative", 
        "type": "text"
      }, 
      {
        "name": "f17", 
        "type": "real"
      }, 
      {
        "name": "f20", 
        "type": "text"
      }, 
      {
        "name": "g_doors_if_decorative", 
        "type": "text"
      }, 
      {
        "name": "h_porches", 
        "type": "text"
      }, 
      {
        "name": "historic_property_name", 
        "type": "text"
      }, 
      {
        "name": "historic_use", 
        "type": "text"
      }, 
      {
        "name": "history_associated_events_people_dates", 
        "type": "text"
      }, 
      {
        "name": "local_landmark_evaluation_currently_listed_yes_no_date", 
        "type": "text"
      }, 
      {
        "name": "number_of_stories", 
        "type": "real"
      }, 
      {
        "name": "other_comments", 
        "type": "text"
      }, 
      {
        "name": "pin", 
        "type": "text"
      }, 
      {
        "name": "present_owner", 
        "type": "text"
      }, 
      {
        "name": "present_owner_s_address", 
        "type": "text"
      }, 
      {
        "name": "present_use", 
        "type": "text"
      }, 
      {
        "name": "raised_entry", 
        "type": "text"
      }, 
      {
        "name": "roof_material", 
        "type": "text"
      }, 
      {
        "name": "roof_shape", 
        "type": "text"
      }, 
      {
        "name": "secondary_door", 
        "type": "text"
      }, 
      {
        "name": "surveyor", 
        "type": "text"
      }, 
      {
        "name": "window_type", 
        "type": "text"
      }, 
      {
        "name": "location_1", 
        "type": "text"
      }
    ]
  }, 
  "schemaName": "socrata/data.illinois.gov", 
  "tableName": "ssmma_blue_island_historic_properties"
}