{
  "@id": "https://raw.githubusercontent.com/talos/docker4data/master/data/socrata_cityofnewyork_disposition_of_discourtesy_allegations_2/data.json", 
  "data": {
    "@id": "http://www.opendatacache.com/data.cityofnewyork.us/api/views/xnpc-vebg/rows.csv"
  }, 
  "description": "CCRB: Disposition of Discourtesy Allegations 2008", 
  "maintainer": {
    "@id": "https://github.com/talos/docker4data"
  }, 
  "metadata": {
    "attribution": "Civilian Complaint Review Board (CCRB)", 
    "category": "Public Safety", 
    "description": "CCRB: Disposition of Discourtesy Allegations 2007", 
    "socrata": {
      "@id": "http://www.opendatacache.com/data.cityofnewyork.us/api/views/xnpc-vebg.json"
    }
  }, 
  "name": "Disposition Of Discourtesy Allegations 2007", 
  "schema": {
    "columns": [
      {
        "name": "type_of_abuse_of_authority_allegation", 
        "type": "text"
      }, 
      {
        "name": "substantiated_number", 
        "type": "real"
      }, 
      {
        "name": "sunstantiated_rate", 
        "type": "text"
      }, 
      {
        "name": "exonerated_number", 
        "type": "real"
      }, 
      {
        "name": "exonerated_rate", 
        "type": "text"
      }, 
      {
        "name": "unsubstantiated_number", 
        "type": "real"
      }, 
      {
        "name": "unsubstantiated_rate", 
        "type": "text"
      }, 
      {
        "name": "unfounded_number", 
        "type": "real"
      }, 
      {
        "name": "unfounded_rate", 
        "type": "text"
      }, 
      {
        "name": "officer_unidentified_number", 
        "type": "real"
      }, 
      {
        "name": "officer_unidentified_rate", 
        "type": "text"
      }, 
      {
        "name": "miscellaneous", 
        "type": "real"
      }, 
      {
        "name": "miscellaneous_rate", 
        "type": "text"
      }
    ]
  }, 
  "tableName": "socrata_cityofnewyork_disposition_of_discourtesy_allegations_2"
}