{
  "@id": "https://raw.githubusercontent.com/talos/docker4data/master/data/socrata_govloop_federal_social_media_terms_of_service_agreemen/data.json", 
  "data": {
    "@id": "http://www.opendatacache.com/data.govloop.com/api/views/n2cx-qkiq/rows.csv"
  }, 
  "maintainer": {
    "@id": "https://github.com/talos/docker4data"
  }, 
  "metadata": {
    "socrata": "http://www.opendatacache.com/data.govloop.com/api/views/n2cx-qkiq.json"
  }, 
  "name": "socrata_govloop_federal_social_media_terms_of_service_agreemen", 
  "schema": {
    "columns": [
      {
        "name": "tool_provider", 
        "type": "text"
      }, 
      {
        "name": "type_of_service", 
        "type": "text"
      }, 
      {
        "name": "general_tos", 
        "type": "text"
      }, 
      {
        "name": "negotiated_tos", 
        "type": "text"
      }, 
      {
        "name": "provider_poc", 
        "type": "text"
      }, 
      {
        "name": "poc_email", 
        "type": "text"
      }
    ]
  }
}