{
  "data": "http://www.opendatacache.com/data.ny.gov/api/views/9vgs-jnha/rows.csv", 
  "description": "This dataset provides county\u2010level demographic data (sex, adjudication, age, race/ethnicity, and service setting) for youth admitted to and discharged from the care and custody of the Office of Children and Family Services (OCFS) each year. Data are counted using a youth\u2019s first admission or discharge in a calendar year. Admissions data are aggregate based on the responsible (court) county. Discharges data are aggregate based on the county of residence.", 
  "maintainer": {
    "@id": "https://github.com/talos/docker4data"
  }, 
  "metadata": {
    "attribution": "Office of Children and Family Services (OCFS)", 
    "category": "Human Services", 
    "description": "This dataset provides county\u2010level demographic data (sex, adjudication, age, race/ethnicity, and service setting) for youth admitted to and discharged from the care and custody of the Office of Children and Family Services (OCFS) each year. Data are counted using a youth\u2019s first admission or discharge in a calendar year. Admissions data are aggregate based on the responsible (court) county. Discharges data are aggregate based on the county of residence.", 
    "socrata": {
      "@id": "http://www.opendatacache.com/data.ny.gov/api/views/9vgs-jnha.json"
    }
  }, 
  "name": "Youth Admission and Discharge Demographics:  Beginning 2003", 
  "schema": "socrata/data.ny.gov", 
  "status": "needs review", 
  "table": "youth_admission_and_discharge_demographics_beginning_2003"
}