{
  "@id": "https://raw.githubusercontent.com/talos/docker4data/master/data/socrata_seattle_carto_ctylimit/data.json", 
  "data": {
    "@id": "http://www.opendatacache.com/data.seattle.gov/api/views/eykv-q5y9/rows.csv"
  }, 
  "description": "Delineates north and south boundaries of City of Seattle", 
  "maintainer": {
    "@id": "https://github.com/talos/docker4data"
  }, 
  "metadata": {
    "attribution": "Seattle GIS Program", 
    "category": "Land Base", 
    "description": "Delineates north and south boundaries of City of Seattle", 
    "socrata": {
      "@id": "http://www.opendatacache.com/data.seattle.gov/api/views/eykv-q5y9.json"
    }
  }, 
  "name": "CARTO.CTYLIMIT", 
  "schema": {
    "columns": [
      {
        "name": "objectid", 
        "type": "real"
      }, 
      {
        "name": "shape", 
        "type": "text"
      }, 
      {
        "name": "len", 
        "type": "real"
      }, 
      {
        "name": "shape_length", 
        "type": "real"
      }
    ]
  }, 
  "tableName": "socrata_seattle_carto_ctylimit"
}