{
  "@id": "https://raw.githubusercontent.com/talos/docker4data/master/data/socrata_seattle_carto_ctylimit/data.json", 
  "data": {
    "@id": "http://www.opendatacache.com/data.seattle.gov/api/views/eykv-q5y9/rows.csv"
  }, 
  "maintainer": {
    "@id": "https://github.com/talos/docker4data"
  }, 
  "metadata": {
    "socrata": "http://www.opendatacache.com/data.seattle.gov/api/views/eykv-q5y9.json"
  }, 
  "name": "socrata_seattle_carto_ctylimit", 
  "schema": {
    "columns": [
      {
        "name": "objectid", 
        "type": "real"
      }, 
      {
        "name": "shape", 
        "type": "text"
      }, 
      {
        "name": "len", 
        "type": "real"
      }, 
      {
        "name": "shape_length", 
        "type": "real"
      }
    ]
  }
}