{
  "@id": "https://raw.githubusercontent.com/talos/docker4data/master/data/socrata_edmonton_ca_2012_budget_consultation_survey_household_/data.json", 
  "data": {
    "@id": "http://www.opendatacache.com/data.edmonton.ca/api/views/2crc-aced/rows.csv"
  }, 
  "maintainer": {
    "@id": "https://github.com/talos/docker4data"
  }, 
  "metadata": {
    "socrata": "http://www.opendatacache.com/data.edmonton.ca/api/views/2crc-aced.json"
  }, 
  "name": "socrata_edmonton_ca_2012_budget_consultation_survey_household_", 
  "schema": {
    "columns": [
      {
        "name": "panelistidquestion", 
        "type": "real"
      }, 
      {
        "name": "d1", 
        "type": "real"
      }, 
      {
        "name": "d2", 
        "type": "real"
      }, 
      {
        "name": "d3", 
        "type": "text"
      }, 
      {
        "name": "civic_ward", 
        "type": "real"
      }, 
      {
        "name": "b11", 
        "type": "real"
      }, 
      {
        "name": "b5a_0", 
        "type": "text"
      }, 
      {
        "name": "b5a_1", 
        "type": "text"
      }, 
      {
        "name": "b5a_2", 
        "type": "text"
      }, 
      {
        "name": "b5a_3", 
        "type": "text"
      }, 
      {
        "name": "b5a_4", 
        "type": "text"
      }, 
      {
        "name": "b5a_5", 
        "type": "text"
      }, 
      {
        "name": "b5a_6", 
        "type": "text"
      }, 
      {
        "name": "b5a_7", 
        "type": "text"
      }, 
      {
        "name": "b5a_8", 
        "type": "text"
      }
    ]
  }
}