{
  "data": "http://www.opendatacache.com/data.kingcounty.gov/api/views/ax8b-wymb/rows.csv", 
  "description": "Final election results for 2012 primary; new data format", 
  "maintainer": {
    "@id": "https://github.com/talos/docker4data"
  }, 
  "metadata": {
    "attribution": "King County Elections", 
    "category": "Election results", 
    "description": "Final election results for 2012 primary; new data format", 
    "socrata": {
      "@id": "http://www.opendatacache.com/data.kingcounty.gov/api/views/ax8b-wymb.json"
    }
  }, 
  "name": "NEW FORMAT: August 2012 Primary Results - King County", 
  "schema": "socrata/data.kingcounty.gov", 
  "status": "needs review", 
  "table": "new_format_august_2012_primary_results_king_county"
}