{
  "data": "http://www.opendatacache.com/data.austintexas.gov/api/views/fksj-fw68/rows.csv", 
  "description": "Average cost to repair leaks in the Utility's distribution system", 
  "maintainer": {
    "@id": "https://github.com/talos/docker4data"
  }, 
  "metadata": {
    "attribution": "City of Austin", 
    "category": "Utility", 
    "description": "Average cost to repair leaks in the Utility's distribution system", 
    "socrata": {
      "@id": "http://www.opendatacache.com/data.austintexas.gov/api/views/fksj-fw68.json"
    }
  }, 
  "name": "Average cost for Leak work orders", 
  "schema": "socrata/data.austintexas.gov", 
  "status": "needs review", 
  "table": "average_cost_for_leak_work_orders"
}