{
  "maintainer": {
    "@id": "https://github.com/talos/docker4data"
  }, 
  "schema": {
    "columns": [
      {
        "type": "text", 
        "name": "year"
      }, 
      {
        "type": "real", 
        "name": "public_safety"
      }, 
      {
        "type": "real", 
        "name": "health_care"
      }, 
      {
        "type": "real", 
        "name": "general_government"
      }, 
      {
        "type": "real", 
        "name": "property_taxation"
      }, 
      {
        "type": "real", 
        "name": "fixed_charges"
      }
    ]
  }, 
  "@id": "https://raw.githubusercontent.com/talos/docker4data/master/data/socrata_cookcountycom_general_fund_expenditures_by_category_19/data.json", 
  "name": "socrata_cookcountycom_general_fund_expenditures_by_category_19", 
  "data": {
    "@id": "http://www.opendatacache.com/cookcounty.socrata.com/api/views/3rn9-29p6/rows.csv"
  }
}