{
  "@id": "https://raw.githubusercontent.com/talos/docker4data/master/data/socrata_ok_oklahoma_health_care_facilities/data.json", 
  "data": {
    "@id": "http://www.opendatacache.com/data.ok.gov/api/views/fyhh-4wxs/rows.csv"
  }, 
  "maintainer": {
    "@id": "https://github.com/talos/docker4data"
  }, 
  "metadata": {
    "socrata": "http://www.opendatacache.com/data.ok.gov/api/views/fyhh-4wxs.json"
  }, 
  "name": "socrata_ok_oklahoma_health_care_facilities", 
  "schema": {
    "columns": [
      {
        "name": "health_care_facility_name", 
        "type": "text"
      }, 
      {
        "name": "address", 
        "type": "text"
      }, 
      {
        "name": "city", 
        "type": "text"
      }, 
      {
        "name": "state", 
        "type": "text"
      }, 
      {
        "name": "zip", 
        "type": "text"
      }, 
      {
        "name": "phone1", 
        "type": "text"
      }, 
      {
        "name": "longitude", 
        "type": "real"
      }, 
      {
        "name": "latitude", 
        "type": "real"
      }, 
      {
        "name": "location", 
        "type": "text"
      }
    ]
  }
}