{
  "@id": "https://raw.githubusercontent.com/talos/docker4data/master/data/socrata_seattle_2007_traffic_flow_counts/data.json", 
  "data": {
    "@id": "http://www.opendatacache.com/data.seattle.gov/api/views/2f8y-htmx/rows.csv", 
    "type": "csv"
  }, 
  "description": "Annualized Average Weekday Daily Traffic\r\nTo provide traffic count data that includes ADT(Average daily traffic- 7 day count, includes weekends.  This is an average number, derived from averaging daily traffic volumes for all seven days), AWDT (Average week-day traffic- 5 day count, does not include week-ends. Derived from averaging daily traffic volumes for Monday thru Friday), AM (AM Peak hour, the highest hour count volume in the AM, consisting of four consecutive 15 minute periods that fall between midnight and noon)and PM (PM Peak hour, the highest hour count volume in the PM, consisting of four consecutive 15 minute periods that fall between noon and midnight)peak hour volumes along with study dates.", 
  "maintainer": {
    "@id": "https://github.com/talos/docker4data"
  }, 
  "metadata": {
    "attribution": "Seattle Department of Transportation", 
    "category": "Transportation", 
    "description": "Annualized Average Weekday Daily Traffic\r\nTo provide traffic count data that includes ADT(Average daily traffic- 7 day count, includes weekends.  This is an average number, derived from averaging daily traffic volumes for all seven days), AWDT (Average week-day traffic- 5 day count, does not include week-ends. Derived from averaging daily traffic volumes for Monday thru Friday), AM (AM Peak hour, the highest hour count volume in the AM, consisting of four consecutive 15 minute periods that fall between midnight and noon)and PM (PM Peak hour, the highest hour count volume in the PM, consisting of four consecutive 15 minute periods that fall between noon and midnight)peak hour volumes along with study dates.", 
    "socrata": {
      "@id": "http://www.opendatacache.com/data.seattle.gov/api/views/2f8y-htmx.json"
    }
  }, 
  "name": "2007 Traffic Flow Counts", 
  "schema": {
    "columns": [
      {
        "name": "fid", 
        "type": "real"
      }, 
      {
        "name": "shape", 
        "type": "text"
      }, 
      {
        "name": "downtown", 
        "type": "text"
      }, 
      {
        "name": "compkey", 
        "type": "real"
      }, 
      {
        "name": "stname", 
        "type": "text"
      }, 
      {
        "name": "objectid_1", 
        "type": "real"
      }, 
      {
        "name": "name", 
        "type": "text"
      }, 
      {
        "name": "year", 
        "type": "real"
      }, 
      {
        "name": "segkey", 
        "type": "real"
      }, 
      {
        "name": "aawdt", 
        "type": "real"
      }, 
      {
        "name": "input_stud", 
        "type": "real"
      }, 
      {
        "name": "hpms", 
        "type": "text"
      }, 
      {
        "name": "flow_count", 
        "type": "text"
      }
    ]
  }, 
  "schemaName": "socrata/data.seattle.gov", 
  "tableName": "2007_traffic_flow_counts"
}