{
  "@id": "https://raw.githubusercontent.com/talos/docker4data/master/data/socrata_illinois_idph_ambulatory_surgical_treatment_center_dir/data.json", 
  "data": {
    "@id": "http://www.opendatacache.com/data.illinois.gov/api/views/if58-xnpz/rows.csv"
  }, 
  "maintainer": {
    "@id": "https://github.com/talos/docker4data"
  }, 
  "metadata": {
    "socrata": "http://www.opendatacache.com/data.illinois.gov/api/views/qphf-nedb.json"
  }, 
  "name": "socrata_illinois_idph_ambulatory_surgical_treatment_center_dir", 
  "schema": {
    "columns": [
      {
        "name": "ambulatory_surgical_treatment_center", 
        "type": "text"
      }, 
      {
        "name": "address", 
        "type": "text"
      }, 
      {
        "name": "city", 
        "type": "text"
      }, 
      {
        "name": "zip", 
        "type": "real"
      }, 
      {
        "name": "county", 
        "type": "text"
      }, 
      {
        "name": "phone", 
        "type": "text"
      }, 
      {
        "name": "license_", 
        "type": "real"
      }, 
      {
        "name": "license_expiration_date", 
        "type": "text"
      }
    ]
  }
}