{
  "data": "http://www.opendatacache.com/data.edmonton.ca/api/views/bwpb-bppt/rows.csv", 
  "description": "The 2015 Tax Sale Auction is now closed.", 
  "maintainer": {
    "@id": "https://github.com/talos/docker4data"
  }, 
  "metadata": {
    "attribution": "Assessment and Taxation, Collection Unit", 
    "category": "City Administration", 
    "description": "The 2015 Tax Sale Auction is now closed.", 
    "socrata": {
      "@id": "http://www.opendatacache.com/data.edmonton.ca/api/views/bwpb-bppt.json"
    }
  }, 
  "name": "Public Auction Listing (2015)", 
  "schema": "socrata/data.edmonton.ca", 
  "status": "needs review", 
  "table": "public_auction_listing_2015_"
}