{
  "maintainer": {
    "@id": "https://github.com/talos/docker4data"
  }, 
  "schema": {
    "columns": [
      {
        "type": "text", 
        "name": "name"
      }, 
      {
        "type": "real", 
        "name": "total_units"
      }, 
      {
        "type": "real", 
        "name": "affordable_units"
      }, 
      {
        "type": "text", 
        "name": "organization"
      }, 
      {
        "type": "text", 
        "name": "location_1"
      }
    ]
  }, 
  "@id": "https://raw.githubusercontent.com/talos/docker4data/master/data/socrata_austintexas_affordable_housing_inventory/data.json", 
  "name": "socrata_austintexas_affordable_housing_inventory", 
  "data": {
    "@id": "http://www.opendatacache.com/data.austintexas.gov/api/views/siyu-szxn/rows.csv"
  }
}