{
  "@id": "https://raw.githubusercontent.com/talos/docker4data/master/data/socrata_cms_provider_of_services_file_clia_december_2014/data.json", 
  "data": {
    "@id": "http://www.opendatacache.com/data.cms.gov/api/views/6c3m-8jzf/rows.csv"
  }, 
  "maintainer": {
    "@id": "https://github.com/talos/docker4data"
  }, 
  "metadata": {
    "socrata": "http://www.opendatacache.com/data.cms.gov/api/views/6c3m-8jzf.json"
  }, 
  "name": "socrata_cms_provider_of_services_file_clia_december_2014", 
  "schema": {
    "columns": [
      {
        "name": "prvdr_ctgry_sbtyp_cd", 
        "type": "text"
      }, 
      {
        "name": "prvdr_ctgry_cd", 
        "type": "text"
      }, 
      {
        "name": "chow_cnt", 
        "type": "text"
      }, 
      {
        "name": "chow_dt", 
        "type": "text"
      }, 
      {
        "name": "city_name", 
        "type": "text"
      }, 
      {
        "name": "acptbl_poc_sw", 
        "type": "text"
      }, 
      {
        "name": "cmplnc_stus_cd", 
        "type": "text"
      }, 
      {
        "name": "ssa_cnty_cd", 
        "type": "text"
      }, 
      {
        "name": "cross_ref_provider_number", 
        "type": "text"
      }, 
      {
        "name": "crtfctn_dt", 
        "type": "text"
      }, 
      {
        "name": "elgblty_sw", 
        "type": "text"
      }, 
      {
        "name": "fac_name", 
        "type": "text"
      }, 
      {
        "name": "intrmdry_carr_cd", 
        "type": "text"
      }, 
      {
        "name": "mdcd_vndr_num", 
        "type": "text"
      }, 
      {
        "name": "orgnl_prtcptn_dt", 
        "type": "text"
      }, 
      {
        "name": "chow_prior_dt", 
        "type": "text"
      }, 
      {
        "name": "intrmdry_carr_prior_cd", 
        "type": "text"
      }, 
      {
        "name": "prvdr_num", 
        "type": "text"
      }, 
      {
        "name": "rgn_cd", 
        "type": "text"
      }, 
      {
        "name": "skltn_rec_sw", 
        "type": "text"
      }, 
      {
        "name": "state_cd", 
        "type": "text"
      }, 
      {
        "name": "ssa_state_cd", 
        "type": "text"
      }, 
      {
        "name": "state_rgn_cd", 
        "type": "text"
      }, 
      {
        "name": "st_adr", 
        "type": "text"
      }, 
      {
        "name": "phne_num", 
        "type": "text"
      }, 
      {
        "name": "pgm_trmntn_cd", 
        "type": "text"
      }, 
      {
        "name": "trmntn_exprtn_dt", 
        "type": "text"
      }, 
      {
        "name": "crtfctn_actn_type_cd", 
        "type": "text"
      }, 
      {
        "name": "gnrl_cntl_type_cd", 
        "type": "text"
      }, 
      {
        "name": "zip_cd", 
        "type": "text"
      }, 
      {
        "name": "fips_state_cd", 
        "type": "text"
      }, 
      {
        "name": "fips_cnty_cd", 
        "type": "text"
      }, 
      {
        "name": "cbsa_urbn_rrl_ind", 
        "type": "text"
      }, 
      {
        "name": "cbsa_cd", 
        "type": "text"
      }, 
      {
        "name": "addtnl_st_adr", 
        "type": "text"
      }, 
      {
        "name": "affiliated_provider_number_1", 
        "type": "text"
      }, 
      {
        "name": "affiliated_provider_number_2", 
        "type": "text"
      }, 
      {
        "name": "affiliated_provider_number_3", 
        "type": "text"
      }, 
      {
        "name": "affiliated_provider_number_4", 
        "type": "text"
      }, 
      {
        "name": "affiliated_provider_number_5", 
        "type": "text"
      }, 
      {
        "name": "affiliated_provider_number_6", 
        "type": "text"
      }, 
      {
        "name": "affiliated_provider_number_7", 
        "type": "text"
      }, 
      {
        "name": "affiliated_provider_number_8", 
        "type": "text"
      }, 
      {
        "name": "a2la_acrdtd_cd", 
        "type": "text"
      }, 
      {
        "name": "a2la_acrdtd_y_match_dt", 
        "type": "text"
      }, 
      {
        "name": "a2la_acrdtd_y_match_sw", 
        "type": "text"
      }, 
      {
        "name": "aabb_acrdtd_cd", 
        "type": "text"
      }, 
      {
        "name": "aabb_acrdtd_y_match_dt", 
        "type": "text"
      }, 
      {
        "name": "aabb_acrdtd_y_match_sw", 
        "type": "text"
      }, 
      {
        "name": "aoa_acrdtd_cd", 
        "type": "text"
      }, 
      {
        "name": "aoa_acrdtd_y_match_dt", 
        "type": "text"
      }, 
      {
        "name": "aoa_acrdtd_y_match_sw", 
        "type": "text"
      }, 
      {
        "name": "ashi_acrdtd_cd", 
        "type": "text"
      }, 
      {
        "name": "ashi_acrdtd_y_match_dt", 
        "type": "text"
      }, 
      {
        "name": "ashi_acrdtd_y_match_sw", 
        "type": "text"
      }, 
      {
        "name": "cap_acrdtd_cd", 
        "type": "text"
      }, 
      {
        "name": "cap_acrdtd_y_match_dt", 
        "type": "text"
      }, 
      {
        "name": "cap_acrdtd_y_match_sw", 
        "type": "text"
      }, 
      {
        "name": "cola_acrdtd_cd", 
        "type": "text"
      }, 
      {
        "name": "cola_acrdtd_y_match_dt", 
        "type": "text"
      }, 
      {
        "name": "cola_acrdtd_y_match_sw", 
        "type": "text"
      }, 
      {
        "name": "jcaho_acrdtd_cd", 
        "type": "text"
      }, 
      {
        "name": "jcaho_acrdtd_y_match_dt", 
        "type": "text"
      }, 
      {
        "name": "jcaho_acrdtd_y_match_sw", 
        "type": "text"
      }, 
      {
        "name": "aplctn_rcvd_dt", 
        "type": "text"
      }, 
      {
        "name": "aplctn_type_cd", 
        "type": "text"
      }, 
      {
        "name": "gnrl_fac_type_cd", 
        "type": "text"
      }, 
      {
        "name": "crtfct_efctv_dt", 
        "type": "text"
      }, 
      {
        "name": "crtfct_mail_dt", 
        "type": "text"
      }, 
      {
        "name": "crtfct_type_cd", 
        "type": "text"
      }, 
      {
        "name": "current_clia_lab_clsfctn_cd", 
        "type": "text"
      }, 
      {
        "name": "clia_lab_classification_cd_1", 
        "type": "text"
      }, 
      {
        "name": "clia_lab_classification_cd_10", 
        "type": "text"
      }, 
      {
        "name": "clia_lab_classification_cd_2", 
        "type": "text"
      }, 
      {
        "name": "clia_lab_classification_cd_3", 
        "type": "text"
      }, 
      {
        "name": "clia_lab_classification_cd_4", 
        "type": "text"
      }, 
      {
        "name": "clia_lab_classification_cd_5", 
        "type": "text"
      }, 
      {
        "name": "clia_lab_classification_cd_6", 
        "type": "text"
      }, 
      {
        "name": "clia_lab_classification_cd_7", 
        "type": "text"
      }, 
      {
        "name": "clia_lab_classification_cd_8", 
        "type": "text"
      }, 
      {
        "name": "clia_lab_classification_cd_9", 
        "type": "text"
      }, 
      {
        "name": "clia_mdcr_num", 
        "type": "text"
      }, 
      {
        "name": "clia_trmntn_cd", 
        "type": "text"
      }, 
      {
        "name": "acrdtn_schdl_cd", 
        "type": "text"
      }, 
      {
        "name": "form_116_acrdtd_test_vol_cnt", 
        "type": "text"
      }, 
      {
        "name": "form_116_test_vol_cnt", 
        "type": "text"
      }, 
      {
        "name": "drctly_afltd_lab_cnt", 
        "type": "text"
      }, 
      {
        "name": "fax_phne_num", 
        "type": "text"
      }, 
      {
        "name": "fy_end_mo_day_cd", 
        "type": "text"
      }, 
      {
        "name": "mlt_site_excptn_sw", 
        "type": "text"
      }, 
      {
        "name": "hosp_lab_excptn_sw", 
        "type": "text"
      }, 
      {
        "name": "non_prft_excptn_sw", 
        "type": "text"
      }, 
      {
        "name": "lab_temp_tstg_site_sw", 
        "type": "text"
      }, 
      {
        "name": "lab_site_cnt", 
        "type": "text"
      }, 
      {
        "name": "ppmp_test_vol_cnt", 
        "type": "text"
      }, 
      {
        "name": "addtnl_fac_name", 
        "type": "text"
      }, 
      {
        "name": "related_provider_number", 
        "type": "text"
      }, 
      {
        "name": "shr_lab_sw", 
        "type": "text"
      }, 
      {
        "name": "shared_lab_xref_number", 
        "type": "text"
      }, 
      {
        "name": "form_1557_crtfct_schdl_cd", 
        "type": "text"
      }, 
      {
        "name": "form_1557_cmplnc_schdl_cd", 
        "type": "text"
      }, 
      {
        "name": "form_1557_test_vol_cnt", 
        "type": "text"
      }, 
      {
        "name": "wvd_test_vol_cnt", 
        "type": "text"
      }
    ]
  }
}