{
  "data": "http://www.opendatacache.com/data.raleighnc.gov/api/views/ytsf-ve44/rows.csv", 
  "description": "Municipal Complex Maintenance FY13 Adopted And FY14 Proposed Budgets", 
  "maintainer": {
    "@id": "https://github.com/talos/docker4data"
  }, 
  "metadata": {
    "attribution": "City of Raleigh Budget and Management Services", 
    "category": "Fiscal Year 2013", 
    "description": "Municipal Complex Maintenance FY13 Adopted And FY14 Proposed Budgets", 
    "socrata": {
      "@id": "http://www.opendatacache.com/data.raleighnc.gov/api/views/ytsf-ve44.json"
    }
  }, 
  "name": "Municipal Complex Maintenance", 
  "schema": "socrata/data.raleighnc.gov", 
  "status": "needs review", 
  "table": "municipal_complex_maintenance"
}