{
  "@id": "https://raw.githubusercontent.com/talos/docker4data/master/data/socrata_bronx_lehman_cuny_bronx_zip_population_and_density/data.json", 
  "data": "http://www.opendatacache.com/bronx.lehman.cuny.edu/api/views/2bxu-nweh/rows.csv", 
  "description": "2010 Census Data on population, pop density, age and ethnicity per zip code", 
  "maintainer": {
    "@id": "https://github.com/talos/docker4data"
  }, 
  "metadata": {
    "attribution": "US Census Bureau", 
    "category": "Population", 
    "description": "2010 Census Data on population, pop density, age and ethnicity per zip code", 
    "socrata": {
      "@id": "http://www.opendatacache.com/bronx.lehman.cuny.edu/api/views/2bxu-nweh.json"
    }
  }, 
  "name": "Bronx Zip Population and  Density", 
  "table": "socrata_bronx_lehman_cuny_bronx_zip_population_and_density"
}