{
  "@id": "https://raw.githubusercontent.com/talos/docker4data/master/data/zoning_boundary_esri_layer_package/data.json", 
  "data": {
    "@id": "http://www.opendatacache.com/data.baltimorecity.gov/download/sbrb-b88sapplication/zip; charset=binary", 
    "type": "application/zip; charset=binary"
  }, 
  "description": "Layer Package representing the zoning districts as defined by the City's Department of Planning. Last Updated 2008", 
  "maintainer": {
    "@id": "https://github.com/talos/docker4data"
  }, 
  "metadata": {
    "attribution": "EGIS", 
    "category": "Geographic", 
    "description": "Layer Package representing the zoning districts as defined by the City's Department of Planning. Last Updated 2008", 
    "socrata": {
      "@id": "http://www.opendatacache.com/data.baltimorecity.gov/api/views/sbrb-b88s.json"
    }
  }, 
  "name": "Zoning Boundary - ESRI Layer Package", 
  "schema": {
    "columns": []
  }, 
  "schemaName": "socrata/data.baltimorecity.gov", 
  "tableName": "zoning_boundary_esri_layer_package"
}