{
  "data": "http://www.opendatacache.com/data.baltimorecity.gov/download/fgsy-8jrm/application/zip", 
  "description": "Polygon feature representing photogrammetrically captured hydrographic information, including lakes, ponds, harbors, waterways, reservoirs, and hidden hydrography used to provide continuous topology. Last Updated 2008", 
  "load": "TODO: zip", 
  "maintainer": {
    "@id": "https://github.com/talos/docker4data"
  }, 
  "metadata": {
    "attribution": "MOIT - GIS", 
    "category": "Geographic", 
    "description": "Polygon feature representing photogrammetrically captured hydrographic information, including lakes, ponds, harbors, waterways, reservoirs, and hidden hydrography used to provide continuous topology. Last Updated 2008", 
    "socrata": {
      "@id": "http://www.opendatacache.com/data.baltimorecity.gov/api/views/fgsy-8jrm.json"
    }
  }, 
  "name": "Water - Shape", 
  "schema": "socrata/data.baltimorecity.gov", 
  "status": "needs review", 
  "table": "water_shape"
}