{
  "@id": "https://raw.githubusercontent.com/talos/docker4data/master/data/socrata_cookcountycom_administrative_hearings_top_5_sheriff_s_/data.json", 
  "data": {
    "@id": "http://www.opendatacache.com/cookcounty.socrata.com/api/views/wp8p-jvuw/rows.csv"
  }, 
  "description": "Data covers December 1, 2010 through September 22, 2011", 
  "maintainer": {
    "@id": "https://github.com/talos/docker4data"
  }, 
  "metadata": {
    "attribution": "Cook County Department of Administrative Hearings", 
    "category": "Courts", 
    "description": "Data covers December 1, 2010 through September 22, 2011", 
    "socrata": {
      "@id": "http://www.opendatacache.com/cookcounty.socrata.com/api/views/wp8p-jvuw.json"
    }
  }, 
  "name": "Administrative Hearings - Top 5 Sheriff's Police Violations - Fiscal Year 2011 Incomplete", 
  "schema": {
    "columns": [
      {
        "name": "violation_code", 
        "type": "text"
      }, 
      {
        "name": "top_5_violations_report_12_1_2010_9_22_2011", 
        "type": "text"
      }, 
      {
        "name": "number_of_violations", 
        "type": "real"
      }
    ]
  }, 
  "tableName": "socrata_cookcountycom_administrative_hearings_top_5_sheriff_s_"
}