{
  "data": "http://www.opendatacache.com/data.hawaii.gov/api/views/jxj3-wzqf/rows.csv", 
  "maintainer": {
    "@id": "https://github.com/talos/docker4data"
  }, 
  "metadata": {
    "socrata": {
      "@id": "http://www.opendatacache.com/data.hawaii.gov/api/views/jxj3-wzqf.json"
    }
  }, 
  "name": "Report Card 3d Resident Sentiment Island Expense Locals", 
  "schema": "socrata/data.hawaii.gov", 
  "status": "needs review", 
  "table": "report_card_3d_resident_sentiment_island_expense_locals"
}