{
  "@id": "https://raw.githubusercontent.com/talos/docker4data/master/data/boundaries_tax_increment_financing_districts/data.json", 
  "data": {
    "@id": "http://www.opendatacache.com/data.cityofchicago.org/api/views/fz5x-7zak/rows.csv"
  }, 
  "description": "Tax Increment Financing (TIF) district boundaries in Chicago. The data can be viewed on the Chicago Data Portal with a web browser. However, to view or use the files outside of a web browser, you will need to use compression software and special GIS software, such as ESRI ArcGIS (shapefile) or Google Earth (KML or KMZ), is required.", 
  "maintainer": {
    "@id": "https://github.com/talos/docker4data"
  }, 
  "metadata": {
    "attribution": "City of Chicago", 
    "category": "Community & Economic Development", 
    "description": "Tax Increment Financing (TIF) district boundaries in Chicago. To view or use these files, compression software and special GIS software, such as ESRI ArcGIS, is required.", 
    "socrata": {
      "@id": "http://www.opendatacache.com/data.cityofchicago.org/api/views/iyec-2es5.json"
    }
  }, 
  "name": "Boundaries - Tax Increment Financing Districts", 
  "schema": {
    "columns": []
  }, 
  "tableName": "boundaries_tax_increment_financing_districts"
}