{
  "@id": "https://raw.githubusercontent.com/talos/docker4data/master/data/socrata_sunlightlabs_supporting_akin_opposing_mccaskill/data.json", 
  "data": {
    "@id": "http://www.opendatacache.com/data.sunlightlabs.com/api/views/6wx9-5np5/rows.csv", 
    "type": "csv"
  }, 
  "maintainer": {
    "@id": "https://github.com/talos/docker4data"
  }, 
  "metadata": {
    "socrata": {
      "@id": "http://www.opendatacache.com/data.sunlightlabs.com/api/views/6wx9-5np5.json"
    }
  }, 
  "name": "Supporting Akin/Opposing McCaskill", 
  "schema": {
    "columns": [
      {
        "name": "date", 
        "type": "timestamp"
      }, 
      {
        "name": "amount", 
        "type": "real"
      }
    ]
  }, 
  "schemaName": "socrata/data.sunlightlabs.com", 
  "tableName": "supporting_akin_opposing_mccaskill"
}