{
  "maintainer": {
    "@id": "https://github.com/talos/docker4data"
  }, 
  "schema": {
    "columns": [
      {
        "type": "real", 
        "name": "district_number"
      }, 
      {
        "type": "text", 
        "name": "district"
      }, 
      {
        "type": "real", 
        "name": "school_number"
      }, 
      {
        "type": "text", 
        "name": "school"
      }, 
      {
        "type": "text", 
        "name": "subject"
      }, 
      {
        "type": "real", 
        "name": "grade_level"
      }, 
      {
        "type": "real", 
        "name": "_2012_total_count"
      }, 
      {
        "type": "real", 
        "name": "_2012_unsatisfactory_count"
      }, 
      {
        "type": "real", 
        "name": "_2012_unsatisfactory"
      }, 
      {
        "type": "real", 
        "name": "_2012_partially_proficient_count"
      }, 
      {
        "type": "real", 
        "name": "_2012_partially_proficient"
      }, 
      {
        "type": "real", 
        "name": "_2012_proficient_count"
      }, 
      {
        "type": "real", 
        "name": "_2012_proficient"
      }, 
      {
        "type": "real", 
        "name": "_2012_advanced_count"
      }, 
      {
        "type": "real", 
        "name": "_2012_advanced"
      }, 
      {
        "type": "real", 
        "name": "_2012_proficient_advanced"
      }, 
      {
        "type": "real", 
        "name": "_2012_no_score_count"
      }, 
      {
        "type": "real", 
        "name": "_2012_no_score"
      }, 
      {
        "type": "real", 
        "name": "_2013_total_count"
      }, 
      {
        "type": "real", 
        "name": "_2013_unsatisfactory_count"
      }, 
      {
        "type": "real", 
        "name": "_2013_unsatisfactory"
      }, 
      {
        "type": "real", 
        "name": "_2013_partially_proficient_count"
      }, 
      {
        "type": "real", 
        "name": "_2013_partially_proficient"
      }, 
      {
        "type": "real", 
        "name": "_2013_proficient_count"
      }, 
      {
        "type": "real", 
        "name": "_2013_proficient"
      }, 
      {
        "type": "real", 
        "name": "_2013_advanced_count"
      }, 
      {
        "type": "real", 
        "name": "_2013_advanced"
      }, 
      {
        "type": "real", 
        "name": "_2013_proficient_advanced"
      }, 
      {
        "type": "real", 
        "name": "_2013_no_score_count"
      }, 
      {
        "type": "real", 
        "name": "_2013_no_score"
      }, 
      {
        "type": "text", 
        "name": "free_and_reduced_lunch"
      }
    ]
  }, 
  "@id": "https://raw.githubusercontent.com/talos/docker4data/master/data/socrata_colorado_tcap_school_and_district_summary_results_2012/data.json", 
  "name": "socrata_colorado_tcap_school_and_district_summary_results_2012", 
  "data": {
    "@id": "http://www.opendatacache.com/data.colorado.gov/api/views/v348-5e6t/rows.csv"
  }
}