{
  "data": "http://www.opendatacache.com/data.wa.gov/api/views/79vd-sdqn/rows.csv", 
  "description": "Jobs sustained from the expendatures or loans from the Public Works Board from 2000 to present, just using the main three programs", 
  "maintainer": {
    "@id": "https://github.com/talos/docker4data"
  }, 
  "metadata": {
    "attribution": "Public Works Board", 
    "category": "Economics", 
    "description": "Jobs sustained from the expendatures or loans from the Public Works Board from 2000 to present, just using the main three programs", 
    "socrata": {
      "@id": "http://www.opendatacache.com/data.wa.gov/api/views/79vd-sdqn.json"
    }
  }, 
  "name": "Job Sustainment", 
  "schema": "socrata/data.wa.gov", 
  "status": "needs review", 
  "table": "job_sustainment"
}