{
  "data": "http://www.opendatacache.com/data.edmonton.ca/api/views/x7r5-d4hj/rows.csv", 
  "description": "In 2010, Capital City Clean Up initiated a Graffiti Vandalism Audit to assess the amount of graffiti vandalism found in the neighbourhoods in Edmonton with the highest reported incidences of graffiti.  A follow-up audit was completed in 2011 to determine if there were significant changes to the amount of graffiti found.  This data set is result of the 2010 Graffiti Vandalism Audit.", 
  "maintainer": {
    "@id": "https://github.com/talos/docker4data"
  }, 
  "metadata": {
    "attribution": "Community Services - Capital City Cleanup", 
    "category": "Environmental Services", 
    "description": "In 2010, Capital City Clean Up initiated a Graffiti Vandalism Audit to assess the amount of graffiti vandalism found in the neighbourhoods in Edmonton with the highest reported incidences of graffiti.  A follow-up audit was completed in 2011 to determine if there were significant changes to the amount of graffiti found.  This data set is result of the 2010 Graffiti Vandalism Audit.", 
    "socrata": {
      "@id": "http://www.opendatacache.com/data.edmonton.ca/api/views/x7r5-d4hj.json"
    }
  }, 
  "name": "2010 Graffiti Audit", 
  "schema": "socrata/data.edmonton.ca", 
  "status": "needs review", 
  "table": "2010_graffiti_audit"
}