{
  "@id": "https://raw.githubusercontent.com/talos/docker4data/master/data/retail_fuel_pump_prices_since_feb_2013_to_may_2015/data.json", 
  "data": {
    "@id": "http://www.opendatacache.com/opendata.go.ke/api/views/vxct-947b/rows.csv", 
    "type": "csv"
  }, 
  "description": "This dataset archives changes in the average fuel pump prices for the nation and can be broken down to changes across major towns as listed on the website of the Energy Regulatory Commission.", 
  "maintainer": {
    "@id": "https://github.com/talos/docker4data"
  }, 
  "metadata": {
    "attribution": "Energy Regulatory Commision", 
    "category": "Energy Pricing", 
    "description": "This dataset archives changes in the average fuel pump prices for the nation and can be broken down to changes across major towns as listed on the website of the Energy Regulatory Commission.", 
    "socrata": {
      "@id": "http://www.opendatacache.com/opendata.go.ke/api/views/vxct-947b.json"
    }
  }, 
  "name": "Retail Fuel Pump Prices since Feb 2013 to May 2015", 
  "schema": {
    "columns": [
      {
        "name": "town", 
        "type": "text"
      }, 
      {
        "name": "super", 
        "type": "real"
      }, 
      {
        "name": "diesel", 
        "type": "real"
      }, 
      {
        "name": "kerosene", 
        "type": "real"
      }, 
      {
        "name": "regular", 
        "type": "real"
      }, 
      {
        "name": "start", 
        "type": "timestamp"
      }, 
      {
        "name": "end", 
        "type": "timestamp"
      }
    ]
  }, 
  "schemaName": "socrata/opendata.go.ke", 
  "tableName": "retail_fuel_pump_prices_since_feb_2013_to_may_2015"
}