{
  "data": "http://www.opendatacache.com/data.acgov.org/api/geospatial/yza6-6jwu", 
  "description": "Alameda County Schools", 
  "load": "ogr2ogr", 
  "maintainer": {
    "@id": "https://github.com/talos/docker4data"
  }, 
  "metadata": {
    "attribution": "US Department of Education", 
    "category": "Education", 
    "description": "Alameda County Schools", 
    "socrata": {
      "@id": "http://www.opendatacache.com/data.acgov.org/api/views/yza6-6jwu.json"
    }
  }, 
  "name": "Alameda County Schools", 
  "schema": "socrata/data.acgov.org", 
  "status": "needs review", 
  "table": "alameda_county_schools"
}