{
  "@id": "https://raw.githubusercontent.com/talos/docker4data/master/data/measure_13_percentage_of_the_nonelderly_population_with_health_insurance_coverage_by_metropolitan_status/data.json", 
  "data": {
    "@id": "http://www.opendatacache.com/healthmeasures.aspe.hhs.gov/api/views/qpa5-frk8/rows.csv", 
    "type": "csv"
  }, 
  "description": "Individuals whose MSA is not identified are excluded from this analysis.", 
  "maintainer": {
    "@id": "https://github.com/talos/docker4data"
  }, 
  "metadata": {
    "description": "Individuals whose MSA is not identified are excluded from this analysis.", 
    "socrata": {
      "@id": "http://www.opendatacache.com/healthmeasures.aspe.hhs.gov/api/views/qpa5-frk8.json"
    }
  }, 
  "name": "Measure 13 : Percentage of the Nonelderly Population with Health Insurance Coverage by Metropolitan Status", 
  "schema": {
    "columns": [
      {
        "name": "measure_value", 
        "type": "text"
      }, 
      {
        "name": "year", 
        "type": "text"
      }, 
      {
        "name": "rural_urban", 
        "type": "text"
      }
    ]
  }, 
  "schemaName": "socrata/healthmeasures.aspe.hhs.gov", 
  "tableName": "measure_13_percentage_of_the_nonelderly_population_with_health_insurance_coverage_by_metropolitan_status"
}