{
  "@id": "https://raw.githubusercontent.com/talos/docker4data/master/data/libraries_children_s_summer_reading_program/data.json", 
  "data": {
    "@id": "http://www.opendatacache.com/data.cityofchicago.org/api/views/gy9e-qh3y/rows.csv"
  }, 
  "description": "The Chicago Public Library Summer Reading Program is an eight-week thematic reading program planned to encourage and instill the love of reading and enjoyment of books in children and teens while promoting the development of their reading interests.", 
  "maintainer": {
    "@id": "https://github.com/talos/docker4data"
  }, 
  "metadata": {
    "attribution": "Chicago Public Library", 
    "category": "Education", 
    "description": "The Chicago Public Library Summer Reading Program is an eight-week thematic reading program planned to encourage and instill the love of reading and enjoyment of books in children and teens while promoting the development of their reading interests.", 
    "socrata": {
      "@id": "http://www.opendatacache.com/data.cityofchicago.org/api/views/gy9e-qh3y.json"
    }
  }, 
  "name": "Libraries - Children's Summer Reading Program", 
  "schema": {
    "columns": [
      {
        "name": "year", 
        "type": "text"
      }, 
      {
        "name": "participants", 
        "type": "real"
      }, 
      {
        "name": "books_read", 
        "type": "real"
      }, 
      {
        "name": "junior_volunteers", 
        "type": "real"
      }, 
      {
        "name": "junior_volunteer_hours", 
        "type": "real"
      }
    ]
  }, 
  "tableName": "libraries_children_s_summer_reading_program"
}