{
  "@id": "https://raw.githubusercontent.com/talos/docker4data/master/data/socrata_cityofnewyork_financial_empowerment_centers/data.json", 
  "data": {
    "@id": "http://www.opendatacache.com/data.cityofnewyork.us/api/views/dt2z-amuf/rows.csv"
  }, 
  "description": "This is a list of the Department of Consumer Affairs' Financial Empowerment Centers. It includes the Financial Empowerment Center site name/partners, site location, hours, and languages spoken.", 
  "maintainer": {
    "@id": "https://github.com/talos/docker4data"
  }, 
  "metadata": {
    "attribution": "Department of Consumer Affairs (DCA)", 
    "category": "Business", 
    "description": "This is a list of the Department of Consumer Affairs' Financial Empowerment Centers. It includes the Financial Empowerment Center site name/partners, site location, hours, and languages spoken.", 
    "socrata": {
      "@id": "http://www.opendatacache.com/data.cityofnewyork.us/api/views/dt2z-amuf.json"
    }
  }, 
  "name": "Financial Empowerment Centers", 
  "schema": {
    "columns": [
      {
        "name": "provider", 
        "type": "text"
      }, 
      {
        "name": "host_organization", 
        "type": "text"
      }, 
      {
        "name": "site_location_address", 
        "type": "text"
      }, 
      {
        "name": "city", 
        "type": "text"
      }, 
      {
        "name": "zip_code", 
        "type": "real"
      }, 
      {
        "name": "days_open", 
        "type": "text"
      }, 
      {
        "name": "hours", 
        "type": "text"
      }, 
      {
        "name": "language_s", 
        "type": "text"
      }, 
      {
        "name": "telephone", 
        "type": "text"
      }
    ]
  }, 
  "tableName": "socrata_cityofnewyork_financial_empowerment_centers"
}